[{
    "filename": "/img/the-soundscape.png",
    "caption": "Where analogue warmth meets digital ghosts"
}, {
    "filename": "/img/between-places.png",
    "caption": "Liminal spaces. Where thoughts wander and songs are born."
}, {
    "filename": "/img/acoustic-guitar.png",
    "caption": "Sometimes only Bob Dylan covers will do."
}, {
    "filename": "/img/walking-flaming.png",
    "caption": "It's not a walk of shame. It's a walk of flame."
}, {
    "filename": "/img/dream-worlds.png",
    "caption": "Fallen cities, floating islands, fading dreams."
}, {
    "filename": "/img/live-in-the-dream.png",
    "caption": "Music for midnight minds."
}, {
    "filename": "/img/oneirina-live.png",
    "caption": "In the moment. Songs from dreams, made real."
}, {
    "filename": "/img/glitch-waltz.png",
    "caption": "Synths, glitches and ghosts. Dancing in the in-between."
} , {
    "filename": "/img/electronic-heart.png",
    "caption": "Beats that breathe. Melodies that linger."
}, {
    "filename": "/img/underground-dreams.png",
    "caption": "Basements, warehouses and late nights. Where the dreamers come alive."
}, {
    "filename": "/img/live-in-the-inbetween.png",
    "caption": "Not here, not there. Just the music."
}, {
    "filename": "/img/city-of-signals.png",
    "caption": "A million lights. A million stories"
}, {
    "filename": "/img/crowd-connection.png",
    "caption": "One heartbeat. All in."
}, {
    "filename": "/img/daydreamer.png",
    "caption": "Sun, sound and space. Lost in music."
}, {
    "filename": "/img/festival-freedom.png",
    "caption": "Loud, bright, unapologetic. Music, movement, me."
}, {
    "filename": "/img/glitch-and-glow.png",
    "caption": "Digital dreams. Real feelings."
}, {
    "filename": "/img/night-lights.png",
    "caption": "Beats under the stars. Glitch-pop energy."
}, {
    "filename": "/img/sunset-sets.png",
    "caption": "Golden hour, open air. Setting the tone."
}]
